contextgem/__init__.py
contextgem/internal/__init__.py
contextgem/internal/data_models.py
contextgem/internal/decorators.py
contextgem/internal/items.py
contextgem/internal/loggers.py
contextgem/internal/utils.py
contextgem/internal/base/__init__.py
contextgem/internal/base/attrs.py
contextgem/internal/base/concepts.py
contextgem/internal/base/examples.py
contextgem/internal/base/instances.py
contextgem/internal/base/items.py
contextgem/internal/base/llms.py
contextgem/internal/base/md_text.py
contextgem/internal/base/mixins.py
contextgem/internal/base/paras_and_sents.py
contextgem/internal/base/serialization.py
contextgem/internal/converters/__init__.py
contextgem/internal/converters/docx/__init__.py
contextgem/internal/converters/docx/base.py
contextgem/internal/converters/docx/exceptions.py
contextgem/internal/converters/docx/namespaces.py
contextgem/internal/converters/docx/package.py
contextgem/internal/converters/docx/utils.py
contextgem/internal/llm_output_structs/__init__.py
contextgem/internal/llm_output_structs/aspect_structs.py
contextgem/internal/llm_output_structs/concept_structs.py
contextgem/internal/llm_output_structs/utils.py
contextgem/internal/typings/__init__.py
contextgem/internal/typings/aliases.py
contextgem/internal/typings/strings_to_types.py
contextgem/internal/typings/typed_class_utils.py
contextgem/internal/typings/types_normalization.py
contextgem/internal/typings/types_to_strings.py
contextgem/internal/typings/user_type_hints_validation.py
contextgem/public/__init__.py
contextgem/public/aspects.py
contextgem/public/concepts.py
contextgem/public/data_models.py
contextgem/public/documents.py
contextgem/public/examples.py
contextgem/public/images.py
contextgem/public/llms.py
contextgem/public/paragraphs.py
contextgem/public/pipelines.py
contextgem/public/sentences.py
contextgem/public/utils.py
contextgem/public/converters/__init__.py
contextgem/public/converters/docx.py
documiner-0.8.2.dist-info/licenses/LICENSE
documiner-0.8.2.dist-info/licenses/NOTICE
documiner-0.8.2.dist-info/METADATA
documiner-0.8.2.dist-info/WHEEL
documiner-0.8.2.dist-info/top_level.txt
documiner-0.8.2.dist-info/RECORD
