Metadata-Version: 2.4
Name: documiner
Version: 0.8.2
Summary: Advanced tool designed for text analysis and data mining in documents
Home-page: https://github.com/sabih-urrehman/documiner
Author: Sahib Ur rehman
Author-email: sabih-urrehman <rodrigonotion02@outlook.com>
Maintainer-email: sabih-urrehman <rodrigonotion02@outlook.com>
License: Apache-2.0
Project-URL: Homepage, https://github.com/sabih-urrehman/documiner
Project-URL: Documentation, https://github.com/sabih-urrehman/documiner/blob/main/README.md
Project-URL: Repository, https://github.com/sabih-urrehman/documiner.git
Project-URL: Bug Tracker, https://github.com/sabih-urrehman/documiner/issues
Keywords: artificial-intelligence,aspect-extraction,automated-prompting,concept-extraction,content-extraction,context-aware,documiner,contract-analysis,contract-automation,contract-intelligence,contract-management,contract-parsing,contract-review,data-extraction,document,document-analysis,document-extraction,document-intelligence,document-parsing,document-pipeline,document-processing,document-qa,document-understanding,docx,entity-extraction,extraction-justifications,extraction-pipeline,fintech,g
Classifier: Development Status :: 4 - Beta
Classifier: Intended Audience :: Developers
Classifier: Intended Audience :: Education
Classifier: Intended Audience :: Financial and Insurance Industry
Classifier: Intended Audience :: Information Technology
Classifier: Intended Audience :: Legal Industry
Classifier: Intended Audience :: Science/Research
Classifier: License :: OSI Approved :: Apache Software License
Classifier: Operating System :: OS Independent
Classifier: Programming Language :: Python :: 3
Classifier: Programming Language :: Python :: 3.10
Classifier: Programming Language :: Python :: 3.11
Classifier: Programming Language :: Python :: 3.12
Classifier: Programming Language :: Python :: 3.13
Classifier: Topic :: Education
Classifier: Topic :: Office/Business
Classifier: Topic :: Scientific/Engineering :: Artificial Intelligence
Classifier: Topic :: Scientific/Engineering :: Image Recognition
Classifier: Topic :: Scientific/Engineering :: Information Analysis
Classifier: Topic :: Software Development :: Libraries :: Application Frameworks
Classifier: Topic :: Software Development :: Libraries :: Python Modules
Classifier: Topic :: Text Processing :: General
Classifier: Topic :: Text Processing :: Linguistic
Requires-Python: >=3.6
License-File: LICENSE
License-File: NOTICE
Requires-Dist: pydantic<3.0.0,>=2.10.6
Requires-Dist: aiolimiter<2.0.0,>=1.2.1
Requires-Dist: jinja2<4.0.0,>=3.1.5
Requires-Dist: loguru<0.8.0,>=0.7.3
Requires-Dist: python-ulid<4.0.0,>=3.0.0
Requires-Dist: litellm<1.71.2,>=1.68.0
Requires-Dist: lxml<6.0.0,>=5.4.0
Requires-Dist: wtpsplit-lite<0.3.0,>=0.2.0
Dynamic: author
Dynamic: home-page
Dynamic: license-file
Dynamic: requires-python
